skinidaov/__init__.py
skinidaov-0.1.8.dist-info/licenses/LICENSE
skinidaov-0.1.8.dist-info/METADATA
skinidaov-0.1.8.dist-info/WHEEL
skinidaov-0.1.8.dist-info/top_level.txt
skinidaov-0.1.8.dist-info/RECORD
