Metadata-Version: 2.4
Name: skinidaov
Version: 0.1.8
Summary: Một bộ chuyển đổi ID đơn giản của Ron AOV
Author: Ron AOV
Author-email: ronlatoiday@gmail.com
License: MIT
Classifier: Programming Language :: Python :: 3
Classifier: License :: OSI Approved :: MIT License
Requires-Python: >=3.6
License-File: LICENSE
Dynamic: author
Dynamic: author-email
Dynamic: classifier
Dynamic: description
Dynamic: description-content-type
Dynamic: license
Dynamic: license-file
Dynamic: requires-python
Dynamic: summary
